vistabnet/__init__.py
vistabnet/trainer.py
vistabnet/vistabnet.py
vistabnet/vistabnet_backbone.py
vistabnet-0.1.1.dist-info/METADATA
vistabnet-0.1.1.dist-info/WHEEL
vistabnet-0.1.1.dist-info/RECORD
