Metadata-Version: 2.1
Name: vistabnet
Version: 0.1.1
Summary: 
Author: wwydmanski
Author-email: wwydmanski@gmail.com
Requires-Python: >=3.9,<4.0
Classifier: Programming Language :: Python :: 3
Classifier: Programming Language :: Python :: 3.9
Classifier: Programming Language :: Python :: 3.10
Classifier: Programming Language :: Python :: 3.11
Classifier: Programming Language :: Python :: 3.12
Requires-Dist: focal-loss-torch (>=0.1.2,<0.2.0)
Requires-Dist: torch (>=2,<3)
Requires-Dist: torchvision (>=0.15.0,<0.16.0)
Requires-Dist: tqdm (>=4.65.0,<5.0.0)
